odoo/addons/resource_calendar_schedule_iteration/README.rst
odoo/addons/resource_calendar_schedule_iteration/__init__.py
odoo/addons/resource_calendar_schedule_iteration/__manifest__.py
odoo/addons/resource_calendar_schedule_iteration/hooks.py
odoo/addons/resource_calendar_schedule_iteration/data/ir_config_parameter_data.xml
odoo/addons/resource_calendar_schedule_iteration/i18n/resource_calendar_schedule_iteration.pot
odoo/addons/resource_calendar_schedule_iteration/model/__init__.py
odoo/addons/resource_calendar_schedule_iteration/model/resource_calendar.py
odoo/addons/resource_calendar_schedule_iteration/readme/CONFIGURE.rst
odoo/addons/resource_calendar_schedule_iteration/readme/CONTRIBUTORS.rst
odoo/addons/resource_calendar_schedule_iteration/readme/DESCRIPTION.rst
odoo/addons/resource_calendar_schedule_iteration/static/description/icon.png
odoo/addons/resource_calendar_schedule_iteration/static/description/index.html
odoo/addons/resource_calendar_schedule_iteration/tests/__init__.py
odoo/addons/resource_calendar_schedule_iteration/tests/test_resource_calendar_schedule_iteration.py
odoo11_addon_resource_calendar_schedule_iteration-11.0.1.0.0.99.dev4.dist-info/METADATA
odoo11_addon_resource_calendar_schedule_iteration-11.0.1.0.0.99.dev4.dist-info/WHEEL
odoo11_addon_resource_calendar_schedule_iteration-11.0.1.0.0.99.dev4.dist-info/top_level.txt
odoo11_addon_resource_calendar_schedule_iteration-11.0.1.0.0.99.dev4.dist-info/RECORD
